bebop/__init__.py
bebop/__main__.py
bebop/bookmarks.py
bebop/colors.py
bebop/command_line.py
bebop/config.py
bebop/downloads.py
bebop/external.py
bebop/fs.py
bebop/gemtext.py
bebop/help.py
bebop/history.py
bebop/identity.py
bebop/links.py
bebop/metalines.py
bebop/mime.py
bebop/mouse.py
bebop/navigation.py
bebop/page.py
bebop/page_pad.py
bebop/plugins.py
bebop/preferences.py
bebop/protocol.py
bebop/rendering.py
bebop/textbox.py
bebop/tofu.py
bebop/welcome.py
bebop/browser/browser.py
bebop/browser/file.py
bebop/browser/gemini.py
bebop/browser/web.py
bebop_browser-0.3.1.dist-info/METADATA
bebop_browser-0.3.1.dist-info/WHEEL
bebop_browser-0.3.1.dist-info/entry_points.txt
bebop_browser-0.3.1.dist-info/top_level.txt
bebop_browser-0.3.1.dist-info/RECORD
