Metadata-Version: 2.1
Name: bebop-browser
Version: 0.3.1
Summary: Terminal browser for Gemini
Home-page: https://git.dece.space/Dece/Bebop
Author: dece
Author-email: shgck@pistache.land
License: GPLv3
Platform: UNKNOWN
Classifier: Environment :: Console
Classifier: Programming Language :: Python :: 3
Classifier: Programming Language :: Python :: 3.7
Requires-Python: >= 3.7
